inclupp/__main__.py
inclupp-1.0.1.dist-info/licenses/LICENSE
inclupp-1.0.1.dist-info/METADATA
inclupp-1.0.1.dist-info/WHEEL
inclupp-1.0.1.dist-info/entry_points.txt
inclupp-1.0.1.dist-info/top_level.txt
inclupp-1.0.1.dist-info/RECORD
