Metadata-Version: 2.4
Name: inclupp
Version: 1.0.1
Summary: A CLI tool to preprocess and compile C++ files with remote #includes.
Home-page: https://github.com/LautyDev/inclupp
Author: LautyDev
Author-email: git@lauty.dev
Project-URL: Bug Tracker, https://github.com/LautyDev/inclupp/issues
Project-URL: Source, https://github.com/LautyDev/inclupp
Project-URL: Documentation, https://github.com/LautyDev/inclupp#readme
Classifier: Programming Language :: Python :: 3
Classifier: License :: OSI Approved :: MIT License
Classifier: Operating System :: OS Independent
Requires-Python: >=3.6
License-File: LICENSE
Requires-Dist: requests
Requires-Dist: colorama
Dynamic: author
Dynamic: author-email
Dynamic: classifier
Dynamic: description
Dynamic: description-content-type
Dynamic: home-page
Dynamic: license-file
Dynamic: project-url
Dynamic: requires-dist
Dynamic: requires-python
Dynamic: summary
